b2cloud/__init__.py
b2cloud/utilities.py
b2cloud-0.2.0.dist-info/LICENSE
b2cloud-0.2.0.dist-info/METADATA
b2cloud-0.2.0.dist-info/WHEEL
b2cloud-0.2.0.dist-info/RECORD
