Metadata-Version: 2.1
Name: b2cloud
Version: 0.2.0
Summary: ヤマト運輸株式会社が提供する送り状発行システムB2クラウドをpythonで利用するパッケージ
Home-page: https://www.interman.jp/
License: MIT
Author: hgs-interman
Author-email: naofumi.higashikawauchi@interman.co.jp
Requires-Python: >=3.9,<4.0
Classifier: License :: OSI Approved :: MIT License
Classifier: Programming Language :: Python :: 3
Classifier: Programming Language :: Python :: 3.9
Classifier: Programming Language :: Python :: 3.10
Classifier: Programming Language :: Python :: 3.11
Requires-Dist: PyMuPDF (>=1.21.1,<2.0.0)
Requires-Dist: lxml (>=4.9.2,<5.0.0)
Requires-Dist: requests (>=2.28.1,<3.0.0)
Project-URL: Documentation, https://github.com/interman-corp/b2cloud
Project-URL: Repository, https://github.com/interman-corp/b2cloud
